asu/__init__.py
asu/cli.py
asu/display.py
asu/s3.py
asu_cli-0.0.2.dist-info/LICENSE
asu_cli-0.0.2.dist-info/METADATA
asu_cli-0.0.2.dist-info/WHEEL
asu_cli-0.0.2.dist-info/entry_points.txt
asu_cli-0.0.2.dist-info/top_level.txt
asu_cli-0.0.2.dist-info/RECORD
