Metadata-Version: 2.1
Name: asu-cli
Version: 0.0.2
Summary: aws s3 utils
Home-page: https://github.com/tekumara/asu
License: UNKNOWN
Platform: UNKNOWN
Classifier: Programming Language :: Python :: 3
Classifier: License :: OSI Approved :: MIT License
Classifier: Operating System :: OS Independent
Requires-Python: >=3.7
Requires-Dist: boto3 (==1.17.44)
Requires-Dist: typer (==0.3.2)
Requires-Dist: rich (==10.0.1)
Provides-Extra: dev
Requires-Dist: autopep8 (==1.5.6) ; extra == 'dev'
Requires-Dist: boto3-stubs[s3] (==1.17.44.0) ; extra == 'dev'
Requires-Dist: importlib-metadata (==3.10.0) ; extra == 'dev'
Requires-Dist: isort (==5.8.0) ; extra == 'dev'
Requires-Dist: flake8 (==3.9.0) ; extra == 'dev'
Requires-Dist: flake8-annotations (==2.6.1) ; extra == 'dev'
Requires-Dist: flake8-colors (==0.1.9) ; extra == 'dev'
Requires-Dist: pre-commit (==2.11.1) ; extra == 'dev'
Requires-Dist: pytest (==6.2.2) ; extra == 'dev'
Requires-Dist: twine (==3.4.1) ; extra == 'dev'
